{
    "data": {
      "services": [
        {
          "id": "ckz4c30qd07720mvz0qnvkxzh",
          "title_en": "Cleaning ",
          "title_az": "Təmizlik",
          "title_ru": "Уборка",
          "cover_img": {
            "publicUrl": "https://res.cloudinary.com/dtokoknba/image/upload/v1648456132/service-photos/cl1ag7w0r00010mxsfmkbej89.webp"
          },
          "subServices": [
            {
              "id": "ckzoiheoa1181930myr5nvtkved",
              "title_en": "Laundry services",
              "title_az": "Çamaşırxana xidmətləri",
              "title_ru": "Услуги прачечной"
            },
            {
              "id": "ckzoimybb1185240myrwgwso0ku",
              "title_en": "Disinsection / Disinfection",
              "title_az": "Dezinseksiya / Dezinfeksiya",
              "title_ru": "Дезинсекция / Дезинфекция"
            },
            {
              "id": "cl0w87fj790200mz54ogs6suy",
              "title_en": "Window cleaning ",
              "title_az": "Pəncərənin təmizlənməsi",
              "title_ru": "Мойка окон"
            },
            {
              "id": "ckz4cfwmm10220mvzf1xrbq1b",
              "title_en": "Home Cleaning",
              "title_az": "Ev təmizliyi",
              "title_ru": "Уборка квартиры"
            },
            {
              "id": "ckzoi619j1180030myradgszv5a",
              "title_en": "Office / Object cleaning",
              "title_az": "Ofis / Obyekt təmizliyi",
              "title_ru": "Уборка офиса, объекта"
            },
            {
              "id": "ckzoilke11184470myrvlk4mtsq",
              "title_en": "Carpets cleaning",
              "title_az": "Xalça / kovrolit təmizliyi",
              "title_ru": "Чистка ковров"
            },
            {
              "id": "cl0up71ul74410mtva3iymgib",
              "title_en": "Cleaning of facades and showcases",
              "title_az": "Fasadların və vitrinlərin təmizlənməsi",
              "title_ru": "Мойка фасадов и витрин"
            },
            {
              "id": "ckz4ci5y710740mvzxldicccm",
              "title_en": "Upholstered furniture Cleaning ",
              "title_az": "Yumşaq mebellərin təmizliyi",
              "title_ru": "Чистка мягкой мебели"
            },
            {
              "id": "ckzoiipoj1182700myrunzrb9xm",
              "title_en": "Curtain and Blinds Cleaning",
              "title_az": "Pərdə və jalüzlərin təmizliyi",
              "title_ru": "Чистка штор и жалюзи"
            },
            {
              "id": "ckzoik62g1183700myrwrfhrdon",
              "title_en": "Pool / fountain cleaning",
              "title_az": "Hovuz / fəvvarələrin təmizliyi",
              "title_ru": "Чистка бассейнов/фонтанов"
            },
            {
              "id": "ckzoinux61186170myr4pwru7m7",
              "title_en": "Bathroom Cleaning",
              "title_az": "Hamam təmizliyi",
              "title_ru": "Уборка ванной комнаты"
            },
            {
              "id": "cl0utzngw152950mtvimii1mjp",
              "title_en": "Daily Cleaning",
              "title_az": "Günlük təmizlik",
              "title_ru": "Gunluk temizlik ru"
            },
            {
              "id": "ckz4cgjbl10480mvzb06wzk0n",
              "title_en": "Car Cleaning",
              "title_az": "Avtomobil təmizliyi",
              "title_ru": "Чистка автомобиля"
            }
          ]
        },
        {
          "id": "ckz4c3x5908230mvz7gmu10mb",
          "title_en": "Home Repair",
          "title_az": "Ev Təmiri",
          "title_ru": "Ремонт дома",
          "cover_img": {
            "publicUrl": "https://res.cloudinary.com/dtokoknba/image/upload/v1648456244/service-photos/cl1agaa8s00020mxs51nta5fa.webp"
          },
          "subServices": [
            {
              "id": "ckzvon42q12090myf2hpsh6zo",
              "title_en": "Furniture repair",
              "title_az": "Mebel təmiri",
              "title_ru": "Furniture repair works ru"
            },
            {
              "id": "ckzvp96w322930myft27vox6z",
              "title_en": "Repair of large and small household appliances",
              "title_az": "Böyük və kiçik məişət texnikası təmiri",
              "title_ru": "Ремонт крупной и мелкой бытовой техники"
            },
            {
              "id": "ckzvp7au622410myfdhe4kwg7",
              "title_en": "Electrical services",
              "title_az": "Elektrik xidmətləri",
              "title_ru": "Услуги электрика"
            },
            {
              "id": "ckzvp8inp22670myfaktfbr55",
              "title_en": "Digital electronic equipment repair",
              "title_az": "Rəqəmsal avadanlıqların təmiri",
              "title_ru": "Ремонт цифровой техники"
            },
            {
              "id": "ckz4qjrsp1798txslmtck90xr",
              "title_en": "Plumbing repair",
              "title_az": "Santexnika təmiri",
              "title_ru": "Ремонт сантехники"
            },
            {
              "id": "ckzvpadz323450myfud6co9sf",
              "title_en": "Minor repair work",
              "title_az": "Xırda təmir işləri",
              "title_ru": "Мелкие ремонтные работы"
            },
            {
              "id": "ckzvpayrt23710myfbbyxaoh7",
              "title_en": "Installation services",
              "title_az": "Quraşdırma xidmətləri",
              "title_ru": "Услуги установки"
            }
          ]
        },
        {
          "id": "ckz4c6bdb08740mvzh3nyqp41",
          "title_en": "Beauty",
          "title_az": "Gözəllik və sağlamlıq",
          "title_ru": "Красота и здоровье",
          "cover_img": {
            "publicUrl": "https://res.cloudinary.com/dtokoknba/image/upload/v1648456255/service-photos/cl1agaiwi00030mxsa2kk1q08.webp"
          },
          "subServices": [
            {
              "id": "ckzs4yupg205450mt9w6wb3y9z",
              "title_en": "Massage",
              "title_az": "Masaj",
              "title_ru": "Массаж"
            },
            {
              "id": "ckzs5ajey213060mt9tqqx1pis",
              "title_en": "Laser hair removal",
              "title_az": "Lazer epilyasiyası",
              "title_ru": "Лазерная эпиляция"
            },
            {
              "id": "ckzs5psoa221420mt9pely0fc9",
              "title_en": "Nutritionist",
              "title_az": "Diyetoloq",
              "title_ru": "Диетолог"
            },
            {
              "id": "ckzs5l6uw217680mt9xy7cpgay",
              "title_en": "Makeup",
              "title_az": "Makiyaj",
              "title_ru": "Макияж"
            },
            {
              "id": "ckzs803jf255670mt97mz5z43d",
              "title_en": "Manicure",
              "title_az": "Manikür",
              "title_ru": "Маникюр"
            },
            {
              "id": "ckzs89gs5261000mt9gdhfwyct",
              "title_en": "Pedicure",
              "title_az": "Pedikür",
              "title_ru": "Педикюр"
            },
            {
              "id": "ckzs59g8g211830mt99oko0jmq",
              "title_en": "Waxing",
              "title_az": "Parafinlə (vosk) epilyasiya",
              "title_ru": "Депиляция воском"
            },
            {
              "id": "cl0w86loc89430mz5s8godke6",
              "title_en": "Personal shopper",
              "title_az": "Şəxsi alış-veriş köməkçisi",
              "title_ru": "Личный ассистент покупок"
            }
          ]
        },
        {
          "id": "ckz4c8hsa09250mvztuu88a8h",
          "title_en": "Events",
          "title_az": "Tədbirlər",
          "title_ru": "Мероприятия ",
          "cover_img": {
            "publicUrl": "https://res.cloudinary.com/dtokoknba/image/upload/v1648456276/service-photos/cl1agaz4g00040mxsfi2oglhj.webp"
          },
          "subServices": [
            {
              "id": "ckzoj2pkz1187100myr76qrbw8s",
              "title_en": "Corporate Events",
              "title_az": "Korporativ tədbirlər",
              "title_ru": "Корпоративные мероприятия "
            },
            {
              "id": "ckzoj8bi71189410myrfwecmnhj",
              "title_en": "Engagement Day",
              "title_az": "Nişan günü",
              "title_ru": "День помолвки"
            },
            {
              "id": "cl0lhxjbf35740m1155oz8bye",
              "title_en": "Photo and Video",
              "title_az": "Foto və Video",
              "title_ru": "Фото и видео"
            },
            {
              "id": "ckzoj9puy1190180myrsvs0ednt",
              "title_en": "Birthday",
              "title_az": "Ad günü",
              "title_ru": "День рождения"
            },
            {
              "id": "ckzojb8151191510myrzx0tau3s",
              "title_en": "Holiday Events",
              "title_az": "Bayram tədbirləri",
              "title_ru": "Праздничное мероприятие"
            },
            {
              "id": "ckzoj7ct11188640myr2580m65s",
              "title_en": "Henna Party",
              "title_az": "Xınayaxdı mərasimi",
              "title_ru": "Девичник"
            },
            {
              "id": "ckzoj3wpi1187870myrd5ijnwid",
              "title_en": "Wedding",
              "title_az": "Toy",
              "title_ru": "Организация свадеб"
            },
            {
              "id": "ckzojcjj01192280myr90rdy9jw",
              "title_en": "Signing ceremonies",
              "title_az": "İmza mərasimləri",
              "title_ru": "Регистрация брака"
            }
          ]
        },
        {
          "id": "ckzsdgyzq363830mt9vmxcade1",
          "title_en": "Design",
          "title_az": "Dizayn",
          "title_ru": "Дизайн",
          "cover_img": {
            "publicUrl": "https://res.cloudinary.com/dtokoknba/image/upload/v1648456289/service-photos/cl1agb98y00050mxsfisz7glt.webp"
          },
          "subServices": []
        },
        {
          "id": "ckzsdjm7f365830mt96cn3iuxf",
          "title_en": "Photo and Video",
          "title_az": "Foto və Video",
          "title_ru": "Фото и видео",
          "cover_img": {
            "publicUrl": "https://res.cloudinary.com/dtokoknba/image/upload/v1645188023/service-photos/ckzsegyqq000c0mt98r33gvv1.jpg"
          },
          "subServices": []
        },
        {
          "id": "ckzvokp1909790myfy1fr0mia",
          "title_en": "Furniture",
          "title_az": "Mebel işləri",
          "title_ru": "Мебель ",
          "cover_img": {
            "publicUrl": "https://res.cloudinary.com/dtokoknba/image/upload/v1648456302/service-photos/cl1agbjgt00060mxse6kzg5x7.webp"
          },
          "subServices": [
            {
              "id": "ckzvom23m10550myf4kfp34xi",
              "title_en": "Office furniture production",
              "title_az": "Ofis mebeli istehsalı",
              "title_ru": "Производство офисной мебели"
            },
            {
              "id": "ckzvomjjg11320myf8lqo834x",
              "title_en": "Home furniture production",
              "title_az": "Ev mebeli istehsalı",
              "title_ru": "Производство домашней мебели"
            }
          ]
        },
        {
          "id": "cl1vtugaj29220m16atlnv2jo",
          "title_en": "Education",
          "title_az": "Təhsil",
          "title_ru": "Təhsil",
          "cover_img": {
            "publicUrl": "https://res.cloudinary.com/dtokoknba/image/upload/v1649752636/service-photos/cl1vw4gdl00010m16gmsjg5kn.jpg"
          },
          "subServices": [
            {
              "id": "cl1vu0lzg37140m16myy6qww4",
              "title_en": "Programing",
              "title_az": "Proqramlaşdırma",
              "title_ru": "Proqramlaşdırma"
            }
          ]
        },
        {
          "id": "cl38v4dau672150muy9lwi09tz",
          "title_en": "Home Animals care",
          "title_az": "Ev Heyvanlarına qayğı",
          "title_ru": "Уход за домашними животными",
          "cover_img": {
            "publicUrl": "https://res.cloudinary.com/dtokoknba/image/upload/v1652716092/service-photos/cl38whlut00030muy6p837gti.jpg"
          },
          "subServices": [
            {
              "id": "cl38wgaka702250muyxxensbud",
              "title_en": "It gəzdirmək",
              "title_az": "It gəzdirmək",
              "title_ru": "It gəzdirmək"
            }
          ]
        }
      ]
    }
  }